odoo10_addon_account_balance_reporting_xlsx-10.0.1.0.0.99.dev7-nspkg.pth
odoo/addons/account_balance_reporting_xlsx/README.rst
odoo/addons/account_balance_reporting_xlsx/__init__.py
odoo/addons/account_balance_reporting_xlsx/__manifest__.py
odoo/addons/account_balance_reporting_xlsx/i18n/account_balance_reporting_xlsx.pot
odoo/addons/account_balance_reporting_xlsx/i18n/bg.po
odoo/addons/account_balance_reporting_xlsx/i18n/ca.po
odoo/addons/account_balance_reporting_xlsx/i18n/de.po
odoo/addons/account_balance_reporting_xlsx/i18n/es.po
odoo/addons/account_balance_reporting_xlsx/i18n/es_ES.po
odoo/addons/account_balance_reporting_xlsx/i18n/eu.po
odoo/addons/account_balance_reporting_xlsx/i18n/gl.po
odoo/addons/account_balance_reporting_xlsx/i18n/hr.po
odoo/addons/account_balance_reporting_xlsx/i18n/pl.po
odoo/addons/account_balance_reporting_xlsx/i18n/pt.po
odoo/addons/account_balance_reporting_xlsx/i18n/sl.po
odoo/addons/account_balance_reporting_xlsx/report/__init__.py
odoo/addons/account_balance_reporting_xlsx/report/report.xml
odoo/addons/account_balance_reporting_xlsx/report/reporting_xlsx.py
odoo/addons/account_balance_reporting_xlsx/static/description/icon.png
odoo/addons/account_balance_reporting_xlsx/static/description/icon.svg
odoo/addons/account_balance_reporting_xlsx/tests/__init__.py
odoo/addons/account_balance_reporting_xlsx/tests/test_account_balance_reporting_xlsx.py
odoo/addons/account_balance_reporting_xlsx/wizard/__init__.py
odoo/addons/account_balance_reporting_xlsx/wizard/account_balance_reporting_wizard.xml
odoo/addons/account_balance_reporting_xlsx/wizard/wizard_print.py
odoo10_addon_account_balance_reporting_xlsx-10.0.1.0.0.99.dev7.dist-info/METADATA
odoo10_addon_account_balance_reporting_xlsx-10.0.1.0.0.99.dev7.dist-info/WHEEL
odoo10_addon_account_balance_reporting_xlsx-10.0.1.0.0.99.dev7.dist-info/namespace_packages.txt
odoo10_addon_account_balance_reporting_xlsx-10.0.1.0.0.99.dev7.dist-info/top_level.txt
odoo10_addon_account_balance_reporting_xlsx-10.0.1.0.0.99.dev7.dist-info/RECORD
