Metadata-Version: 2.1
Name: odoo10-addon-account-balance-reporting-xlsx
Version: 10.0.1.0.0.99.dev7
Summary: Export Account balance reporting to XLSX
Home-page: https://odoospain.odoo.com
Author: Spanish Localization Team,Odoo Community Association (OCA)
Author-email: support@odoo-community.org
License: AGPL-3
Platform: UNKNOWN
Classifier: Programming Language :: Python
Classifier: Framework :: Odoo
Classifier: License :: OSI Approved :: GNU Affero General Public License v3
Requires-Python: ~=2.7
Requires-Dist: odoo10-addon-account-balance-reporting
Requires-Dist: odoo10-addon-report-xlsx
Requires-Dist: odoo (<10.1dev,>=10.0)
